{"이미지 정보":{"이미지 식별자":778318,"이미지 높이":800,"이미지 파일명":"▼10.26 알바-2020_09-1-20200910-1-nt2251k09-스텔라(318)0910얼굴옆모습이나가린거이쁜거살려주세요,제품컷컬러로모델맞춰주세요,몸매보정PSD확인,9번예시로작업-14-IMG_2533.JPG","이미지 너비":800},"데이터셋 정보":{"파일 생성일자":"2020-11-02 18:30:34","데이터셋 상세설명":{"렉트좌표":{"아우터":[{}],"하의":[{}],"원피스":[{}],"상의":[{"X좌표":390.683,"Y좌표":306.172,"가로":184,"세로":208}]},"폴리곤좌표":{"아우터":[{}],"하의":[{}],"원피스":[{}],"상의":[{"X좌표8":498.067,"X좌표9":0.0,"Y좌표9":0.0,"X좌표2":391.183,"Y좌표4":515.445,"X좌표3":402.171,"Y좌표3":514.446,"Y좌표2":307.671,"X좌표1":452.117,"Y좌표1":306.672,"X좌표6":575.982,"Y좌표8":309.668,"X좌표7":539.022,"Y좌표7":329.647,"X좌표4":498.067,"Y좌표6":423.545,"X좌표5":557.003,"Y좌표5":498.463}]},"라벨링":{"스타일":[{"스타일":"프레피"}],"아우터":[{}],"하의":[{}],"원피스":[{}],"상의":[{"기장":"노멀","색상":"베이지","카테고리":"니트웨어","디테일":["니트꽈베기"],"소매기장":"긴팔","소재":["니트"],"프린트":["무지"],"넥라인":"브이넥","핏":"노멀"}]}},"파일 번호":778318,"파일 이름":"▼10.26 알바-2020_09-1-20200910-1-nt2251k09-스텔라(318)0910얼굴옆모습이나가린거이쁜거살려주세요,제품컷컬러로모델맞춰주세요,몸매보정PSD확인,9번예시로작업-14-IMG_2533.JPG"}}